logeasy/__init__.py
logeasy/handlers.py
logeasy-0.1a0.dist-info/METADATA
logeasy-0.1a0.dist-info/WHEEL
logeasy-0.1a0.dist-info/top_level.txt
logeasy-0.1a0.dist-info/RECORD
