Metadata-Version: 2.1
Name: logeasy
Version: 0.1a0
Summary: Utilities for logging in Python
Home-page: UNKNOWN
Author: Caio Belfort
Author-email: caiobelfort90@gmail.com
License: GPL
Platform: UNKNOWN
Classifier: Development Status :: 3 - Alpha
Classifier: Topic :: Software Development
Classifier: Intended Audience :: Developers
Classifier: Programming Language :: Python :: 3
Classifier: Programming Language :: Python :: 3.7
